claude_bedrock_cli-1.1.1.dist-info/licenses/LICENSE
claude_cli/__init__.py
claude_cli/bedrock_client.py
claude_cli/config.py
claude_cli/configure.py
claude_cli/conversation.py
claude_cli/langsmith_logger.py
claude_cli/main.py
claude_cli/todo_manager.py
claude_cli/tools.py
claude_bedrock_cli-1.1.1.dist-info/METADATA
claude_bedrock_cli-1.1.1.dist-info/WHEEL
claude_bedrock_cli-1.1.1.dist-info/entry_points.txt
claude_bedrock_cli-1.1.1.dist-info/top_level.txt
claude_bedrock_cli-1.1.1.dist-info/RECORD
