Metadata-Version: 2.4
Name: claude-bedrock-cli
Version: 1.1.1
Summary: A powerful CLI for Claude AI using AWS Bedrock - no Anthropic subscription needed
Author: Claude Bedrock CLI Contributors
License-Expression: MIT
Project-URL: Homepage, https://github.com/yourusername/claude-bedrock-cli
Project-URL: Documentation, https://github.com/yourusername/claude-bedrock-cli#readme
Project-URL: Repository, https://github.com/yourusername/claude-bedrock-cli
Project-URL: Issues, https://github.com/yourusername/claude-bedrock-cli/issues
Keywords: claude,ai,cli,aws,bedrock,anthropic,chatbot,assistant
Classifier: Development Status :: 4 - Beta
Classifier: Intended Audience :: Developers
Classifier: Programming Language :: Python :: 3
Classifier: Programming Language :: Python :: 3.8
Classifier: Programming Language :: Python :: 3.9
Classifier: Programming Language :: Python :: 3.10
Classifier: Programming Language :: Python :: 3.11
Classifier: Programming Language :: Python :: 3.12
Classifier: Topic :: Software Development :: Libraries :: Python Modules
Classifier: Topic :: Scientific/Engineering :: Artificial Intelligence
Requires-Python: >=3.8
License-File: LICENSE
Requires-Dist: boto3>=1.34.0
Requires-Dist: anthropic>=0.39.0
Requires-Dist: rich>=13.7.0
Requires-Dist: prompt-toolkit>=3.0.43
Requires-Dist: click>=8.1.7
Requires-Dist: pyyaml>=6.0.1
Requires-Dist: python-dotenv>=1.0.0
Requires-Dist: langsmith>=0.1.0
Provides-Extra: aws
Requires-Dist: awscli>=1.32.0; extra == "aws"
Dynamic: license-file
